dlwheel/__init__.py
dlwheel/backup.py
dlwheel/config.py
dlwheel/setup.py
dlwheel/utils.py
dlwheel/cli/__init__.py
dlwheel/cli/main.py
dlwheel/cli/commands/rlog.py
dlwheel-1.0.12.dist-info/METADATA
dlwheel-1.0.12.dist-info/WHEEL
dlwheel-1.0.12.dist-info/entry_points.txt
dlwheel-1.0.12.dist-info/top_level.txt
dlwheel-1.0.12.dist-info/RECORD
