Metadata-Version: 2.4
Name: dlwheel
Version: 1.0.12
Summary: A lightweight deep learning library.
Author-email: liiuhaao <liiuhaao66@gmail.com>
Requires-Python: >=3.6
Requires-Dist: pathspec>=0.9.0
Requires-Dist: python-box>=6.0.2
Requires-Dist: pyyaml>=6.0.1
